NVRChannel/NVRChannel/__init__.py
NVRChannel/__init__.py
NVRChannel/devices_manifest.json
NVRChannel/onvif/LICENSE
NVRChannel/onvif/README.rst
NVRChannel/onvif/__init__.py
NVRChannel/onvif/cli.py
NVRChannel/onvif/client.py
NVRChannel/onvif/definition.py
NVRChannel/onvif/exceptions.py
NVRChannel/onvif/version.txt
nvrchannel-0.20.0.dist-info/WHEEL
nvrchannel-0.20.0.dist-info/METADATA
nvrchannel-0.20.0.dist-info/RECORD
