Metadata-Version: 2.4
Name: nvrchannel
Version: 0.20.0
Author: Daniel Dunn
License-Expression: MIT
Classifier: License :: OSI Approved :: MIT License
Requires-Dist: opencv-python
Requires-Dist: iot-devices>=0.30.0
Requires-Dist: pillow
Requires-Dist: icemedia
Requires-Dist: scullery
Requires-Dist: zeep
Requires-Python: >=3.10, <4.0
